exogress-0.1.0_alpha.3.dist-info/METADATA
exogress-0.1.0_alpha.3.dist-info/WHEEL
exogress/__init__.py
exogress/exogress.cpython-37m-darwin.so
exogress-0.1.0_alpha.3.dist-info/RECORD
